pyxml2pdf/__init__.py
pyxml2pdf/main.py
pyxml2pdf/core/__init__.py
pyxml2pdf/core/events.py
pyxml2pdf/core/initializer.py
pyxml2pdf/core/parser.py
pyxml2pdf/core/post_processor.py
pyxml2pdf/core/rows.py
pyxml2pdf/core/sorter.py
pyxml2pdf/core/types.py
pyxml2pdf/input/__init__.py
pyxml2pdf/input/custom_properties.py
pyxml2pdf/input/properties.py
pyxml2pdf/styles/__init__.py
pyxml2pdf/styles/table_styles.py
pyxml2pdf/styles/fonts/AUTHORS
pyxml2pdf/styles/fonts/COPYING
pyxml2pdf/styles/fonts/ChangeLog
pyxml2pdf/styles/fonts/LiberationSans-Bold.ttf
pyxml2pdf/styles/fonts/LiberationSans-BoldItalic.ttf
pyxml2pdf/styles/fonts/LiberationSans-Italic.ttf
pyxml2pdf/styles/fonts/LiberationSans-Regular.ttf
pyxml2pdf/styles/fonts/License.txt
pyxml2pdf/styles/fonts/README
pyxml2pdf/styles/fonts/all-free-download.com.url
pyxml2pdf/tables/__init__.py
pyxml2pdf/tables/builder.py
pyxml2pdf/tables/tables.py
pyxml2pdf-0.3.5.dist-info/licenses/LICENSE
pyxml2pdf-0.3.5.dist-info/METADATA
pyxml2pdf-0.3.5.dist-info/WHEEL
pyxml2pdf-0.3.5.dist-info/top_level.txt
pyxml2pdf-0.3.5.dist-info/RECORD
