Metadata-Version: 2.4
Name: pyxml2pdf
Version: 0.3.5
Summary: Transfer XML to well formatted PDF table.
Home-page: https://github.com/BjoernLudwigPTB/pyxml2pdf
Author: Björn Ludwig, Wojciech Kur
Author-email: bjoern.ludwig@ptb.de
Keywords: xml pdf conversion
Classifier: Development Status :: 4 - Beta
Classifier: Topic :: Utilities
Classifier: Topic :: Software Development :: Libraries :: Python Modules
Classifier: License :: OSI Approved :: GNU General Public License v3 (GPLv3)
Classifier: Programming Language :: Python :: 3
Classifier: Programming Language :: Python :: 3.10
Classifier: Programming Language :: Python :: 3.11
Classifier: Programming Language :: Python :: 3.12
Requires-Python: >=3.10
License-File: LICENSE
Requires-Dist: defusedxml
Requires-Dist: download
Requires-Dist: reportlab>=4
Requires-Dist: pypdf
Dynamic: author
Dynamic: author-email
Dynamic: classifier
Dynamic: description
Dynamic: description-content-type
Dynamic: home-page
Dynamic: keywords
Dynamic: license-file
Dynamic: requires-dist
Dynamic: requires-python
Dynamic: summary
